{"schemaVersion":1,"campaignId":"31c63cbe-b856-4bae-81d3-ef6ef34905d7","logo":{"alt":"The secure crypto wallet, built right in the browser. No extension required.","imageUrl":"0-d6501b7a-622d-4d8a-a881-39951c900c74.png","companyName":"Brave Software","destinationUrl":"https://brave.com/wallet?source=sponsoredimage"},"wallpapers":[{"imageUrl":"0-e308f8f2-e4fa-4b4e-9535-528b3e414c54.jpg","focalPoint":{"x":1406,"y":720},"creativeInstanceId":"ba9f2bae-51d1-445a-8d1a-efc656c11664"},{"imageUrl":"0-45fe8dfc-f1b3-496d-a288-1b0e99a8df75.jpg","focalPoint":{"x":1185,"y":720},"logo":{"alt":"The secure crypto wallet, built right in the browser. No extension required.","imageUrl":"0-44a463f8-5579-416d-a525-99ffca788d59.png","companyName":"Brave Software","destinationUrl":"https://brave.com/wallet?source=sponsoredimage"},"creativeInstanceId":"743656d1-1b35-49ae-acf8-8069b0648ba5"}],"campaigns":[{"schemaVersion":1,"campaignId":"31c63cbe-b856-4bae-81d3-ef6ef34905d7","logo":{"alt":"The secure crypto wallet, built right in the browser. No extension required.","imageUrl":"0-d6501b7a-622d-4d8a-a881-39951c900c74.png","companyName":"Brave Software","destinationUrl":"https://brave.com/wallet?source=sponsoredimage"},"wallpapers":[{"imageUrl":"0-e308f8f2-e4fa-4b4e-9535-528b3e414c54.jpg","focalPoint":{"x":1406,"y":720},"creativeInstanceId":"ba9f2bae-51d1-445a-8d1a-efc656c11664"},{"imageUrl":"0-45fe8dfc-f1b3-496d-a288-1b0e99a8df75.jpg","focalPoint":{"x":1185,"y":720},"logo":{"alt":"The secure crypto wallet, built right in the browser. No extension required.","imageUrl":"0-44a463f8-5579-416d-a525-99ffca788d59.png","companyName":"Brave Software","destinationUrl":"https://brave.com/wallet?source=sponsoredimage"},"creativeInstanceId":"743656d1-1b35-49ae-acf8-8069b0648ba5"}]},{"schemaVersion":1,"campaignId":"381508bd-fb10-409e-97b7-30d37e480803","logo":{"alt":"Brave Talk is live! Unlimited private video calls, right in your browser. No apps. No login. Learn More","imageUrl":"1-c95a1a20-641c-46af-9d24-4269230ec63e.png","companyName":"Brave Talk","destinationUrl":"https://brave.com/talk?source=sponsoredimage"},"wallpapers":[{"imageUrl":"1-92743bc3-a05b-4357-8890-9502290a58ce.jpg","focalPoint":{"x":1093,"y":720},"creativeInstanceId":"3aab8847-5209-4309-8cfc-7d1a8bbcd01e"},{"imageUrl":"1-a1a2276e-167a-4d4d-bd0c-4341bc7492dd.jpg","focalPoint":{"x":1646,"y":720},"logo":{"alt":"Brave Talk is live! Unlimited private video calls, right in your browser. No apps. No login. Learn More","imageUrl":"1-9e103c68-3811-45af-87e6-0e8fa08f6e71.png","companyName":"Brave Talk","destinationUrl":"https://brave.com/talk?source=sponsoredimage"},"creativeInstanceId":"a5b10641-5f4c-4352-a251-10cf68a2dafc"}]}]}